ossfs/__init__.py
ossfs/async_oss.py
ossfs/base.py
ossfs/core.py
ossfs/exceptions.py
ossfs/file.py
ossfs/utils.py
ossfs-2023.12.0.dist-info/LICENSE
ossfs-2023.12.0.dist-info/METADATA
ossfs-2023.12.0.dist-info/WHEEL
ossfs-2023.12.0.dist-info/top_level.txt
ossfs-2023.12.0.dist-info/RECORD
